pywhitakers/__init__.py
pywhitakers-0.0.14.dist-info/LICENSE
pywhitakers-0.0.14.dist-info/METADATA
pywhitakers-0.0.14.dist-info/WHEEL
pywhitakers-0.0.14.dist-info/top_level.txt
pywhitakers-0.0.14.dist-info/RECORD
